pg4n/__init__.py
pg4n/cmp_domain_checker.py
pg4n/config_parser.py
pg4n/config_reader.py
pg4n/config_values.py
pg4n/eq_wildcard_checker.py
pg4n/errfmt.py
pg4n/implied_expression_checker.py
pg4n/inconsistent_expression_checker.py
pg4n/main.py
pg4n/psqlconninfo.py
pg4n/psqlparser.py
pg4n/psqlwrapper.py
pg4n/qepparser.py
pg4n/semanticrouter.py
pg4n/sqlparser.py
pg4n/strange_having_checker.py
pg4n/subquery_order_by_checker.py
pg4n/subquery_select_checker.py
pg4n/sum_distinct_checker.py
pg4n/test/__init__.py
pg4n/test/test_cmp_domain_checker.py
pg4n/test/test_config_parser.py
pg4n/test/test_eq_wildcard_checker.py
pg4n/test/test_errfmt.py
pg4n/test/test_implied_expression_checker.py
pg4n/test/test_inconsistent_expression_checker.py
pg4n/test/test_psqlparser.py
pg4n/test/test_psqlwrapper.py
pg4n/test/test_qepparser.py
pg4n/test/test_sqlparser.py
pg4n/test/test_strange_having_checker.py
pg4n/test/test_subquery_order_by_checker.py
pg4n/test/test_subquery_select_checker.py
pg4n/test/test_sum_distinct_checker.py
pg4n/util.py
pg4n-1.0.0.65.dist-info/entry_points.txt
pg4n-1.0.0.65.dist-info/LICENSE
pg4n-1.0.0.65.dist-info/WHEEL
pg4n-1.0.0.65.dist-info/METADATA
pg4n-1.0.0.65.dist-info/RECORD
