Metadata-Version: 2.1
Name: pg4n
Version: 1.0.0.65
Summary: PostgreSQL for novices - helps debug PostgreSQL queries
Author: Joni Nikki
Author-email: joni.nikki@tuni.fi
Requires-Python: >=3.10,<4.0
Classifier: Programming Language :: Python :: 3
Classifier: Programming Language :: Python :: 3.10
Classifier: Programming Language :: Python :: 3.11
Requires-Dist: pexpect (>=4.8.0,<5.0.0)
Requires-Dist: psycopg[binary] (>=3.1.3,<4.0.0)
Requires-Dist: pyparsing (>=3.0.9,<4.0.0)
Requires-Dist: pyte (>=0.8.1,<0.9.0)
Requires-Dist: sqlglot (>=6.3.2,<7.0.0)
